{
  "annotations": {
    "changelogDate": "20240730140451"
  },
  "applications": "*",
  "fields": [
    {
      "fieldName": "id",
      "fieldType": "String"
    },
    {
      "fieldName": "documentname",
      "fieldType": "String"
    },
    {
      "fieldName": "documenttype",
      "fieldType": "Integer"
    },
    {
      "fieldName": "documentsize",
      "fieldType": "Long"
    },
    {
      "fieldName": "secretlevel",
      "fieldType": "Secretlevel",
      "fieldValues": "PUBLIC,INTERNAL,SECRET,CONFIDENTIAL",
      "fieldValuesJavadocs": {
        "PUBLIC": "密级：公开，内部，秘密，机密"
      }
    },
    {
      "fieldName": "url",
      "fieldType": "String"
    },
    {
      "fieldName": "createtime",
      "fieldType": "LocalDate"
    },
    {
      "fieldName": "creatorname",
      "fieldType": "String"
    }
  ],
  "name": "Document",
  "relationships": [
    {
      "otherEntityName": "hrManagement",
      "relationshipName": "creatorid",
      "relationshipSide": "left",
      "relationshipType": "many-to-one"
    },
    {
      "otherEntityName": "projectwbs",
      "relationshipName": "projectwbs",
      "relationshipSide": "left",
      "relationshipType": "many-to-one"
    }
  ],
  "searchEngine": "no",
  "service": "serviceImpl"
}
