{
  "annotations": {
    "changelogDate": "20240914071631"
  },
  "applications": "*",
  "fields": [
    {
      "fieldName": "id",
      "fieldType": "String"
    },
    {
      "fieldName": "startDate",
      "fieldType": "String"
    },
    {
      "fieldName": "endDate",
      "fieldType": "String"
    },
    {
      "fieldName": "leaveType",
      "fieldType": "String"
    },
    {
      "fieldName": "reason",
      "fieldType": "String"
    },
    {
      "fieldName": "status",
      "fieldType": "String"
    }
  ],
  "name": "LeaveApplicationInfo",
  "relationships": [],
  "searchEngine": "no"
}
